trulens/apps/langgraph/__init__.py
trulens/apps/langgraph/inline_evaluations.py
trulens/apps/langgraph/trace_provider.py
trulens/apps/langgraph/tru_graph.py
trulens_apps_langgraph-2.5.3.dist-info/METADATA
trulens_apps_langgraph-2.5.3.dist-info/WHEEL
trulens_apps_langgraph-2.5.3.dist-info/RECORD
